README.rst
setup.py
verticaltable/__init__.py
verticaltable/verticaltable.py
verticaltable.egg-info/PKG-INFO
verticaltable.egg-info/SOURCES.txt
verticaltable.egg-info/dependency_links.txt
verticaltable.egg-info/top_level.txt