Metadata-Version: 1.0
Name: verticaltable
Version: 0.1.0
Summary: VERTICALTABLE structured text parser
Home-page: https://github.com/ytyng/verticaltable.git
Author: ytyng
Author-email: ytyng@live.jp
License: BSD
Keywords: Python,Data structure
Platform: UNKNOWN
